pilkit/__init__.py
pilkit/exceptions.py
pilkit/lib.py
pilkit/pkgmeta.py
pilkit/utils.py
pilkit/processors/__init__.py
pilkit/processors/base.py
pilkit/processors/convert.py
pilkit/processors/crop.py
pilkit/processors/filter.py
pilkit/processors/overlay.py
pilkit/processors/resize.py
pilkit/processors/utils.py
pilkit-3.0.dist-info/AUTHORS
pilkit-3.0.dist-info/LICENSE
pilkit-3.0.dist-info/METADATA
pilkit-3.0.dist-info/WHEEL
pilkit-3.0.dist-info/pbr.json
pilkit-3.0.dist-info/top_level.txt
pilkit-3.0.dist-info/RECORD
