Metadata-Version: 2.1
Name: pilkit
Version: 3.0
Summary: A collection of utilities and processors for the Python Imaging Library.
Home-page: http://github.com/matthewwithanm/pilkit/
Author: Matthew Tretter
Author-email: m@tthewwithanm.com
License: BSD
Classifier: Development Status :: 5 - Production/Stable
Classifier: Intended Audience :: Developers
Classifier: License :: OSI Approved :: BSD License
Classifier: Operating System :: OS Independent
Classifier: Programming Language :: Python :: 3.6
Classifier: Programming Language :: Python :: 3.7
Classifier: Programming Language :: Python :: 3.8
Classifier: Programming Language :: Python :: 3.9
Classifier: Programming Language :: Python :: 3.10
Classifier: Programming Language :: Python :: 3.11
Classifier: Topic :: Utilities
License-File: LICENSE
License-File: AUTHORS
Requires-Dist: Pillow>=7.0
